Prabhu/__init__.py
Prabhu/even.py
Prabhu/perfectsqnum.py
Prabhu-0.0.1.dist-info/LICENSE
Prabhu-0.0.1.dist-info/METADATA
Prabhu-0.0.1.dist-info/WHEEL
Prabhu-0.0.1.dist-info/top_level.txt
Prabhu-0.0.1.dist-info/RECORD
