Metadata-Version: 2.1
Name: Prabhu
Version: 0.0.1
Summary: Python Package to find even numbers in a range and to chech is given number a perfect square or not.
Home-page: UNKNOWN
Author: Prabhu Kiran
Author-email: prabhukiran426@gmail.com
License: UNKNOWN
Platform: UNKNOWN
Classifier: Programming Language :: Python :: 3
Classifier: License :: OSI Approved :: MIT License
Classifier: Operating System :: OS Independent
Requires-Python: >=3.6
License-File: LICENSE
